Workbook
Name Slicer_Payment_Mode: #N/A

Sheet full_30_day_budget_dataset
A1: Date | B1: Month | C1: Category | D1: Sub-Category | E1: Description | F1: Type | G1: Payment Mode | H1: Amount
A2: 46143 | B2: May | C2: Salary | D2: Primary | E2: Monthly Salary | F2: Income | G2: Bank | H2: 150000
A3: 46143 | B3: May | C3: Food | D3: Groceries | E3: Groceries expense | F3: Expense | G3: Card | H3: 1180
A4: 46143 | B4: May | C4: Transport | D4: Public | E4: Public expense | F4: Expense | G4: Card | H4: 650
A5: 46143 | B5: May | C5: Shopping | D5: Electronics | E5: Electronics expense | F5: Expense | G5: UPI | H5: 700
A6: 46143 | B6: May | C6: Bills | D6: Electricity | E6: Electricity expense | F6: Expense | G6: UPI | H6: 1228
A7: 46143 | B7: May | C7: Bills | D7: Electricity | E7: Electricity expense | F7: Expense | G7: Cash | H7: 564
A8: 46143 | B8: May | C8: Food | D8: Snacks | E8: Snacks expense | F8: Expense | G8: Card | H8: 814
A9: 46144 | B9: May | C9: Rent | D9: Housing | E9: Room Rent | F9: Expense | G9: UPI | H9: 6000
A10: 46144 | B10: May | C10: Entertainment | D10: Movies | E10: Movies expense | F10: Expense | G10: Cash | H10: 687
A11: 46144 | B11: May | C11: Transport | D11: Local | E11: Local expense | F11: Expense | G11: Cash | H11: 401
A12: 46144 | B12: May | C12: Shopping | D12: Electronics | E12: Electronics expense | F12: Expense | G12: Cash | H12: 568
A13: 46144 | B13: May | C13: Shopping | D13: Electronics | E13: Electronics expense | F13: Expense | G13: Cash | H13: 1110
... A150: 46172 | B150: May | C150: Transport | D150: Fuel | E150: Fuel expense | F150: Expense | G150: UPI | H150: 1160

Sheet Table and extra information
A5: Date | B5: Month | C5: Category | D5: Sub-Category | E5: Description | F5: Type | G5: Payment Mode | H5: Amount | I5: Day | J5: Day Type
A6: 46143 | B6: May | C6: Salary | D6: Primary | E6: Monthly Salary | F6: Income | G6: Bank | H6: 150000 | I6: =TEXT(Table7[[#This Row],[Date]],"dddd") -> Friday | J6: =IF(OR(Table7[[#This Row],[Day]]="Saturday",Table7[[#This Row],[Day]]="Sunday"),"Weekend","Weekday") -> Weekday
A7: 46143 | B7: May | C7: Food | D7: Groceries | E7: Groceries expense | F7: Expense | G7: Card | H7: 1180 | I7: =TEXT(Table7[[#This Row],[Date]],"dddd") -> Friday | J7: =IF(OR(Table7[[#This Row],[Day]]="Saturday",Table7[[#This Row],[Day]]="Sunday"),"Weekend","Weekday") -> Weekday
A8: 46143 | B8: May | C8: Transport | D8: Public | E8: Public expense | F8: Expense | G8: Card | H8: 650 | I8: =TEXT(Table7[[#This Row],[Date]],"dddd") -> Friday | J8: =IF(OR(Table7[[#This Row],[Day]]="Saturday",Table7[[#This Row],[Day]]="Sunday"),"Weekend","Weekday") -> Weekday
A9: 46143 | B9: May | C9: Shopping | D9: Electronics | E9: Electronics expense | F9: Expense | G9: UPI | H9: 700 | I9: =TEXT(Table7[[#This Row],[Date]],"dddd") -> Friday | J9: =IF(OR(Table7[[#This Row],[Day]]="Saturday",Table7[[#This Row],[Day]]="Sunday"),"Weekend","Weekday") -> Weekday
A10: 46143 | B10: May | C10: Bills | D10: Electricity | E10: Electricity expense | F10: Expense | G10: UPI | H10: 1228 | I10: =TEXT(Table7[[#This Row],[Date]],"dddd") -> Friday | J10: =IF(OR(Table7[[#This Row],[Day]]="Saturday",Table7[[#This Row],[Day]]="Sunday"),"Weekend","Weekday") -> Weekday
A11: 46143 | B11: May | C11: Bills | D11: Electricity | E11: Electricity expense | F11: Expense | G11: Cash | H11: 564 | I11: =TEXT(Table7[[#This Row],[Date]],"dddd") -> Friday | J11: =IF(OR(Table7[[#This Row],[Day]]="Saturday",Table7[[#This Row],[Day]]="Sunday"),"Weekend","Weekday") -> Weekday
A12: 46143 | B12: May | C12: Food | D12: Snacks | E12: Snacks expense | F12: Expense | G12: Card | H12: 814 | I12: =TEXT(Table7[[#This Row],[Date]],"dddd") -> Friday | J12: =IF(OR(Table7[[#This Row],[Day]]="Saturday",Table7[[#This Row],[Day]]="Sunday"),"Weekend","Weekday") -> Weekday
A13: 46144 | B13: May | C13: Rent | D13: Housing | E13: Room Rent | F13: Expense | G13: UPI | H13: 6000 | I13: =TEXT(Table7[[#This Row],[Date]],"dddd") -> Saturday | J13: =IF(OR(Table7[[#This Row],[Day]]="Saturday",Table7[[#This Row],[Day]]="Sunday"),"Weekend","Weekday") -> Weekend
A14: 46144 | B14: May | C14: Entertainment | D14: Movies | E14: Movies expense | F14: Expense | G14: Cash | H14: 687 | I14: =TEXT(Table7[[#This Row],[Date]],"dddd") -> Saturday | J14: =IF(OR(Table7[[#This Row],[Day]]="Saturday",Table7[[#This Row],[Day]]="Sunday"),"Weekend","Weekday") -> Weekend
A15: 46144 | B15: May | C15: Transport | D15: Local | E15: Local expense | F15: Expense | G15: Cash | H15: 401 | I15: =TEXT(Table7[[#This Row],[Date]],"dddd") -> Saturday | J15: =IF(OR(Table7[[#This Row],[Day]]="Saturday",Table7[[#This Row],[Day]]="Sunday"),"Weekend","Weekday") -> Weekend
A16: 46144 | B16: May | C16: Shopping | D16: Electronics | E16: Electronics expense | F16: Expense | G16: Cash | H16: 568 | I16: =TEXT(Table7[[#This Row],[Date]],"dddd") -> Saturday | J16: =IF(OR(Table7[[#This Row],[Day]]="Saturday",Table7[[#This Row],[Day]]="Sunday"),"Weekend","Weekday") -> Weekend
A17: 46144 | B17: May | C17: Shopping | D17: Electronics | E17: Electronics expense | F17: Expense | G17: Cash | H17: 1110 | I17: =TEXT(Table7[[#This Row],[Date]],"dddd") -> Saturday | J17: =IF(OR(Table7[[#This Row],[Day]]="Saturday",Table7[[#This Row],[Day]]="Sunday"),"Weekend","Weekday") -> Weekend
... A154: 46172 | B154: May | C154: Transport | D154: Fuel | E154: Fuel expense | F154: Expense | G154: UPI | H154: 1160 | I154: =TEXT(Table7[[#This Row],[Date]],"dddd") -> Saturday | J154: =IF(OR(Table7[[#This Row],[Day]]="Saturday",Table7[[#This Row],[Day]]="Sunday"),"Weekend","Weekday") -> Weekend

Sheet Date and Day Expense
A1: Type | B1: Expense
A3: Row Labels | B3: Sum of Amount
A4: 46143 | B4: 5136
A5: 46144 | B5: 8982 | F5: Type | G5: Expense
A6: 46145 | B6: 4876
A7: 46146 | B7: 3502 | F7: Row Labels | G7: Sum of Amount
A8: 46147 | B8: 6359 | F8: Sunday | G8: 16944
A9: 46148 | B9: 4182 | F9: Monday | G9: 15394
A10: 46149 | B10: 4164 | F10: Tuesday | G10: 20562
A11: 46150 | B11: 1484 | F11: Wednesday | G11: 14339
A12: 46151 | B12: 4154 | F12: Thursday | G12: 16314
A13: 46152 | B13: 4109 | F13: Friday | G13: 22128
A14: 46153 | B14: 2759 | F14: Saturday | G14: 23033
A15: 46154 | B15: 5120 | F15: Grand Total | G15: 128714
A16: 46155 | B16: 3680
A17: 46156 | B17: 4201
A18: 46157 | B18: 5080
A19: 46158 | B19: 3638
A20: 46159 | B20: 2720
A21: 46160 | B21: 5365
A22: 46161 | B22: 3798
A23: 46162 | B23: 3879
A24: 46163 | B24: 4675
A25: 46164 | B25: 3616
A26: 46165 | B26: 3247
A27: 46166 | B27: 5239
... A33: 46172 | B33: 3012
A34: Grand Total | B34: 128714

Sheet Expense Distribution
A3: Row Labels | B3: Sum of Amount
A4: Bills | B4: 31280
A5: Entertainment | B5: 25046 | K5: Food is the highest expense category
A6: Food | B6: 38740
A7: Rent | B7: 6000
A8: Shopping | B8: 12320
A9: Transport | B9: 15328
A10: Grand Total | B10: 128714

Sheet Mode of payment
A2: Category | B2: (Multiple Items)
B4: Sum of Amount
A5: Card | B5: 34001
A6: Cash | B6: 41599
A7: UPI | B7: 53114
A8: Grand Total | B8: 128714

Sheet Main dashboard
A1: Personal Budget Dashboard | J1: Total Expense | K1: =B4 -> 128714 | M1: Payment Method | N1: Total Spending
A2: Metric | B2: Value | J2: Average Daily Expense | K2: =AVERAGE('Date and Day Expense'!B4:B33) -> 4290.4667 | M2: UPI | N2: =SUMIF(full_30_day_budget_dataset!$G:$G,"UPI",full_30_day_budget_dataset!$H:$H) -> 53114
A3: Total Income | B3: =SUMIFS(Table7[Amount],Table7[Type],"Income") -> 150000 | J3: Highest Single Day Expense | K3: =MAX('Date and Day Expense'!B4:B33) -> 8982 | M3: CASH | N3: =SUMIF(full_30_day_budget_dataset!$G:$G,"Cash",full_30_day_budget_dataset!$H:$H) -> 41599
A4: Total Expense | B4: =SUMIFS(Table7[Amount],Table7[Type],"Expense") -> 128714 | J4: Lowest Single Day Expense | K4: =MIN('Date and Day Expense'!B4:B33) -> 1484 | M4: CARD | N4: =SUMIF(full_30_day_budget_dataset!$G:$G,"Card",full_30_day_budget_dataset!$H:$H) -> 34001
A5: Savings | B5: =B3-B4 -> 21286
A6: Savings % | B6: =(B5/B3) -> 0.14190667
